{
  "id": "cfc2a7422c14d8a7d6d15a59f946aea5ed4d5932",
  "title": "Pope Leo to renew call for peace during first Christmas blessing",
  "summary": "Pope Leo XIV is to deliver his first Christmas “Urbi et Orbi” blessing from Vatican City on Thursday, at the end of a year overshadowed by conflict around the world. The year ends with sources of hope for the Christian community, which celebrated its first festive Christmas in Bethlehem, in the occupied West Bank, since the start of the war in Gaza.",
  "canonicalUrl": "https://www.france24.com/en/europe/20251225-pope-leo-to-renew-call-for-peace-during-first-urbi-et-orbi-christmas-blessing",
  "source": {
    "id": "france24_all",
    "name": "France 24 - Top Stories",
    "url": "https://www.france24.com/en/",
    "feedUrl": "https://www.france24.com/en/rss",
    "country": "FR",
    "language": "en"
  },
  "publishedAt": "2025-12-25T06:56:23.000Z",
  "fetchedAt": "2025-12-25T08:27:16.557Z",
  "category": "world",
  "tags": [
    "Europe"
  ],
  "image": "https://s.france24.com/media/display/ddd5d39a-e15a-11f0-becb-005056bf30b7/w:1024/p:16x9/AP25358797799822.jpg",
  "language": "en",
  "storagePath": "data/articles/world/2025/12/25/cfc2a7422c14d8a7d6d15a59f946aea5ed4d5932.json"
}
