{
  "id": "896be7d961cf3822ec16bc27fea7fe051164813b",
  "title": "Vikes' McCarthy out with hairline fracture in hand",
  "summary": "Vikings quarterback J.J. McCarthy has a \"very small\" hairline fracture in his right hand and will be sidelined for Thursday's Christmas Day game against the Lions, coach Kevin O'Connell said Tuesday.",
  "canonicalUrl": "https://www.espn.com/nfl/story/_/id/47400372/vikings-qb-jj-mccarthy-christmas-day-game-vs-lions-hairline-fracture-hand",
  "source": {
    "id": "espn_news",
    "name": "ESPN - Top Headlines",
    "url": "https://www.espn.com/",
    "feedUrl": "https://www.espn.com/espn/rss/news",
    "country": "US",
    "language": "en"
  },
  "publishedAt": "2025-12-23T23:27:03.000Z",
  "fetchedAt": "2025-12-24T00:05:48.176Z",
  "category": "sports",
  "tags": [],
  "image": null,
  "language": "en",
  "storagePath": "data/articles/sports/2025/12/23/896be7d961cf3822ec16bc27fea7fe051164813b.json"
}
