{
  "id": "8fb9bf300ecf484572060336294c71bff6975918",
  "title": "Weekend attacks in Ukraine bring more casualties, damage infrastructure",
  "summary": "Hostilities in Ukraine this weekend resulted in more civilian casualties and widespread damage to critical infrastructure, the UN Office for the Coordination of Humanitarian Affairs (OCHA) reported on Monday.",
  "canonicalUrl": "https://news.un.org/feed/view/en/story/2025/12/1166652",
  "source": {
    "id": "un_news_all",
    "name": "UN News - All",
    "url": "https://news.un.org/en/",
    "feedUrl": "https://news.un.org/feed/subscribe/en/news/all/rss.xml",
    "country": "UN",
    "language": "en"
  },
  "publishedAt": "2025-12-22T12:00:00.000Z",
  "fetchedAt": "2025-12-24T01:30:41.127Z",
  "category": "world",
  "tags": [],
  "image": "https://global.unitednations.entermediadb.net/assets/mediadb/services/module/asset/downloads/preset/Collections/Embargoed/17-10-2025-UNOCHA-Ukraine-02.jpg/image560x340cropped.jpg",
  "language": "en",
  "storagePath": "data/articles/world/2025/12/22/8fb9bf300ecf484572060336294c71bff6975918.json"
}
