{
  "id": "d787e6c432d7ac91b105fae42cc1e447ec42c93f",
  "title": "2026 FIFA Men's World Cup schedule released. The USA's path and full fixtures.",
  "summary": "FIFA released the World Cup schedule on Saturday that will feature 104 matches spread across 11 cities in the United States, with three in Mexico and two in Canada.",
  "canonicalUrl": "https://www.cbsnews.com/news/2026-fifa-mens-world-cup-schedule-released-full-fixtures",
  "source": {
    "id": "cbs_sports",
    "name": "CBS News - Sports",
    "url": "https://www.cbsnews.com/sports/",
    "feedUrl": "https://www.cbsnews.com/latest/rss/sports",
    "country": "US",
    "language": "en"
  },
  "publishedAt": "2025-12-06T20:37:21.000Z",
  "fetchedAt": "2025-12-24T00:05:49.119Z",
  "category": "sports",
  "tags": [],
  "image": null,
  "language": "en",
  "storagePath": "data/articles/sports/2025/12/06/d787e6c432d7ac91b105fae42cc1e447ec42c93f.json"
}
