{
  "id": "c397f9662947eea8285d4a64b9f381e019ad7230",
  "title": "The best sci-fi movies of 2025. ranked",
  "summary": "Spike your eggnog and relax with our list of the finest flicks of the year about invasive AI, soaring superheroes, and Lovecraftian horrors.",
  "canonicalUrl": "https://www.space.com/entertainment/space-movies-shows/the-best-sci-fi-movies-of-2025-ranked",
  "source": {
    "id": "space_com",
    "name": "Space.com",
    "url": "https://www.space.com/",
    "feedUrl": "https://www.space.com/feeds.xml",
    "country": "US",
    "language": "en"
  },
  "publishedAt": "2025-12-27T13:00:00.000Z",
  "fetchedAt": "2025-12-27T13:29:50.110Z",
  "category": "science",
  "tags": [
    "Space Movies &amp; Shows",
    "Entertainment"
  ],
  "image": "https://cdn.mos.cms.futurecdn.net/fyBgh8FeWB5bE6Ny7kwMFS-1280-80.jpg",
  "language": "en",
  "storagePath": "data/articles/science/2025/12/27/c397f9662947eea8285d4a64b9f381e019ad7230.json"
}
