{
  "id": "b1a075c8bef8d657ecb616dd13da115e7905ebe8",
  "title": "From biting flies to feathered dinosaurs, scientists reveal 70 new species",
  "summary": "Researchers announced over 70 new species in a single year, including bizarre insects, ancient dinosaurs, rare mammals, and deep-river fish. Many were found not in the wild, but in museum collections, proving that major discoveries can still be hiding in plain sight.",
  "canonicalUrl": "https://www.sciencedaily.com/releases/2025/12/251218060552.htm",
  "source": {
    "id": "sciencedaily_science",
    "name": "ScienceDaily - Top Science",
    "url": "https://www.sciencedaily.com/news/top/science/",
    "feedUrl": "https://www.sciencedaily.com/rss/top/science.xml",
    "country": "US",
    "language": "en"
  },
  "publishedAt": "2025-12-19T10:59:30.000Z",
  "fetchedAt": "2025-12-24T00:05:44.956Z",
  "category": "science",
  "tags": [],
  "image": null,
  "language": "en",
  "storagePath": "data/articles/science/2025/12/19/b1a075c8bef8d657ecb616dd13da115e7905ebe8.json"
}
