{
  "id": "60fb3257655f59315a56b9037c3452127dccc438",
  "title": "What to know about the new flu strain as cases rise",
  "summary": "The Centers for Disease Control and Prevention estimates there have been 4.6 million flu cases across the U.S. since the season began. Dr. Amanda Kravitz, a pediatrician at Weill Cornell in New York, explains what to know about rising cases, symptoms to watch for and how to protect your family.",
  "canonicalUrl": "https://www.cbsnews.com/video/what-to-know-about-the-new-flu-strain-as-cases-rise",
  "source": {
    "id": "cbs_health",
    "name": "CBS News - Health",
    "url": "https://www.cbsnews.com/health/",
    "feedUrl": "https://www.cbsnews.com/latest/rss/health",
    "country": "US",
    "language": "en"
  },
  "publishedAt": "2025-12-22T13:46:00.000Z",
  "fetchedAt": "2025-12-24T00:05:46.538Z",
  "category": "health",
  "tags": [],
  "image": null,
  "language": "en",
  "storagePath": "data/articles/health/2025/12/22/60fb3257655f59315a56b9037c3452127dccc438.json"
}
