{
  "id": "8b525ac3153fd9a2f8455e3714cc47a677ec2f56",
  "title": "Brett Harrison, the former president of FTX US, raised a $35M Series A for his new perpetual futures exchange AX, a source says at a $187M valuation (Yueqi Yang/The Information)",
  "summary": "Yueqi Yang / The Information: Brett Harrison, the former president of FTX US, raised a $35M Series A for his new perpetual futures exchange AX, a source says at a $187M valuation — Brett Harrison, the former president of FTX US, has raised $35 million for his startup Architect Financial Technologies, which offers a global perpetual futures exchange.",
  "canonicalUrl": "http://www.techmeme.com/251223/p12",
  "source": {
    "id": "techmeme",
    "name": "Techmeme",
    "url": "https://www.techmeme.com/",
    "feedUrl": "https://www.techmeme.com/feed.xml",
    "country": "US",
    "language": "en"
  },
  "publishedAt": "2025-12-23T14:10:46.000Z",
  "fetchedAt": "2025-12-24T00:05:33.964Z",
  "category": "tech",
  "tags": [],
  "image": null,
  "language": "en",
  "storagePath": "data/articles/tech/2025/12/23/8b525ac3153fd9a2f8455e3714cc47a677ec2f56.json"
}
