{
  "id": "8166017da950113909ea7ed3fa53662bf6c78a30",
  "title": "Sudan PM presents peace plan at UN, calling for a ceasefire",
  "summary": "Sudan's Prime Minister has brought a wide ranging peace plan before the United Nations. But the paramilitary group, the Rapid Support Forces, has yet to sign onto it, and experts say it is unlikely they will, as it demands their withdrawal and disarmament. Story by Ellen Gainsford.",
  "canonicalUrl": "https://www.france24.com/en/video/20251224-sudan-pm-presents-peace-plan-at-un-calling-for-a-ceasefire",
  "source": {
    "id": "france24_all",
    "name": "France 24 - Top Stories",
    "url": "https://www.france24.com/en/",
    "feedUrl": "https://www.france24.com/en/rss",
    "country": "FR",
    "language": "en"
  },
  "publishedAt": "2025-12-24T12:12:43.000Z",
  "fetchedAt": "2025-12-24T14:19:12.479Z",
  "category": "world",
  "tags": [
    ""
  ],
  "image": "https://s.france24.com/media/display/44fb1212-e0be-11f0-815b-005056bfb2b6/w:1024/p:16x9/EN-20251223-214549-214746-CS.jpg",
  "language": "en",
  "storagePath": "data/articles/world/2025/12/24/8166017da950113909ea7ed3fa53662bf6c78a30.json"
}
