{
  "id": "a3b77a8282aeac25afba6dcc7c9fbaa69201d357",
  "title": "Trump calls for release of any Epstein files naming Democrats: \"Embarrass them\"",
  "summary": "As prosecutors contend with a massive trove of Epstein files, President Trump suggested Friday the Justice Department is spending too much time on the issue — but said Democrats should be named.",
  "canonicalUrl": "https://www.cbsnews.com/news/trump-calls-for-release-epstein-files-naming-democrats",
  "source": {
    "id": "cbs_politics",
    "name": "CBS News - Politics",
    "url": "https://www.cbsnews.com/politics/",
    "feedUrl": "https://www.cbsnews.com/latest/rss/politics",
    "country": "US",
    "language": "en"
  },
  "publishedAt": "2025-12-27T00:59:08.000Z",
  "fetchedAt": "2025-12-27T01:19:39.325Z",
  "category": "world",
  "tags": [],
  "image": null,
  "language": "en",
  "storagePath": "data/articles/world/2025/12/27/a3b77a8282aeac25afba6dcc7c9fbaa69201d357.json"
}
